{
    "version": "5.0.1",
    "flags": {},
    "shapes": [
        {
            "label": "Banana",
            "points": [
                [
                    385.01593017578125,
                    214.51568603515625
                ],
                [
                    368.2335510253906,
                    185.0106201171875
                ],
                [
                    366.403564453125,
                    155.06813049316406
                ],
                [
                    284.0673828125,
                    70.31861114501953
                ],
                [
                    305.6836853027344,
                    52.518680572509766
                ],
                [
                    355.18426513671875,
                    100.59228515625
                ],
                [
                    373.64483642578125,
                    118.63467407226562
                ],
                [
                    411.759765625,
                    122.61327362060547
                ],
                [
                    446.8852233886719,
                    152.05332946777344
                ],
                [
                    469.7493591308594,
                    200.52890014648438
                ],
                [
                    494.238037109375,
                    283.2919921875
                ],
                [
                    502.7419738769531,
                    405.4798278808594
                ],
                [
                    496.998046875,
                    492.61749267578125
                ],
                [
                    473.4443359375,
                    571.9754638671875
                ],
                [
                    453.0511779785156,
                    598.22900390625
                ],
                [
                    432.05126953125,
                    602.9937744140625
                ],
                [
                    420.33294677734375,
                    579.6605224609375
                ],
                [
                    415.9927978515625,
                    468.95306396484375
                ],
                [
                    418.7227478027344,
                    349.45501708984375
                ]
            ],
            "group_id": null,
            "shape_type": "polygon",
            "flags": {}
        }
    ],
    "imagePath": "Banana76_aug_2.jpg",
    "imageData": null,
    "imageHeight": 640,
    "imageWidth": 640
}