{
    "version": "5.0.1",
    "flags": {},
    "shapes": [
        {
            "label": "Banana",
            "points": [
                [
                    196.02821350097656,
                    257.08843994140625
                ],
                [
                    222.18478393554688,
                    325.5359802246094
                ],
                [
                    272.6206970214844,
                    399.030517578125
                ],
                [
                    317.2346496582031,
                    448.25701904296875
                ],
                [
                    377.04412841796875,
                    477.178955078125
                ],
                [
                    411.8199768066406,
                    472.4329833984375
                ],
                [
                    444.0638732910156,
                    471.6749267578125
                ],
                [
                    458.1533508300781,
                    432.89422607421875
                ],
                [
                    456.3155212402344,
                    407.53515625
                ],
                [
                    459.9103698730469,
                    380.3589172363281
                ],
                [
                    448.6726989746094,
                    374.21148681640625
                ],
                [
                    456.9927673339844,
                    361.8846740722656
                ],
                [
                    446.1087646484375,
                    347.4039611816406
                ],
                [
                    376.1940002441406,
                    356.17169189453125
                ],
                [
                    337.03521728515625,
                    326.86602783203125
                ],
                [
                    307.650634765625,
                    289.9419250488281
                ],
                [
                    288.77008056640625,
                    250.4708251953125
                ],
                [
                    291.63128662109375,
                    214.60018920898438
                ],
                [
                    284.3702392578125,
                    200.11572265625
                ],
                [
                    310.088623046875,
                    195.379150390625
                ],
                [
                    330.0226135253906,
                    202.60446166992188
                ],
                [
                    336.512451171875,
                    172.16455078125
                ],
                [
                    298.4653625488281,
                    166.76951599121094
                ],
                [
                    272.750732421875,
                    175.12908935546875
                ],
                [
                    247.37286376953125,
                    158.8519287109375
                ],
                [
                    230.32826232910156,
                    142.92840576171875
                ],
                [
                    201.37060546875,
                    168.31944274902344
                ],
                [
                    185.47340393066406,
                    210.72500610351562
                ]
            ],
            "group_id": null,
            "shape_type": "polygon",
            "flags": {}
        }
    ],
    "imagePath": "Banana40_aug_1.jpg",
    "imageData": null,
    "imageHeight": 640,
    "imageWidth": 640
}