{
    "version": "5.0.1",
    "flags": {},
    "shapes": [
        {
            "label": "ChickenPie",
            "points": [
                [
                    166.68312072753906,
                    368.1080322265625
                ],
                [
                    158.07965087890625,
                    293.4144592285156
                ],
                [
                    123.58995819091797,
                    270.0943908691406
                ],
                [
                    132.0965118408203,
                    177.87039184570312
                ],
                [
                    157.308837890625,
                    53.57836151123047
                ],
                [
                    211.48728942871094,
                    0.0
                ],
                [
                    277.348388671875,
                    0.0
                ],
                [
                    397.215087890625,
                    0.0
                ],
                [
                    460.4974060058594,
                    0.0
                ],
                [
                    546.7409057617188,
                    3.7278389930725098
                ],
                [
                    587.37060546875,
                    115.72582244873047
                ],
                [
                    619.7820434570312,
                    236.43145751953125
                ],
                [
                    623.47802734375,
                    379.78057861328125
                ],
                [
                    564.9114379882812,
                    471.16851806640625
                ],
                [
                    497.0487365722656,
                    520.3246459960938
                ],
                [
                    433.9975891113281,
                    553.0086059570312
                ],
                [
                    424.97076416015625,
                    496.12408447265625
                ],
                [
                    305.0461730957031,
                    475.9259338378906
                ],
                [
                    222.61338806152344,
                    399.2411804199219
                ],
                [
                    179.96327209472656,
                    397.1389465332031
                ],
                [
                    168.896484375,
                    372.946533203125
                ]
            ],
            "group_id": null,
            "shape_type": "polygon",
            "flags": {}
        }
    ],
    "imagePath": "ChickenPie81_aug_9.jpg",
    "imageData": null,
    "imageHeight": 640,
    "imageWidth": 640
}