{
    "version": "5.0.1",
    "flags": {},
    "shapes": [
        {
            "label": "ChickenPie",
            "points": [
                [
                    212.25316455696202,
                    226.0253164556962
                ],
                [
                    242.2278481012658,
                    210.63291139240505
                ],
                [
                    270.5822784810127,
                    204.15189873417722
                ],
                [
                    307.8481012658228,
                    192.81012658227849
                ],
                [
                    338.63291139240505,
                    196.86075949367086
                ],
                [
                    372.65822784810126,
                    206.58227848101265
                ],
                [
                    390.48101265822777,
                    226.8354430379747
                ],
                [
                    404.253164556962,
                    243.0379746835443
                ],
                [
                    417.2151898734177,
                    254.37974683544303
                ],
                [
                    409.11392405063293,
                    268.9620253164557
                ],
                [
                    452.0506329113924,
                    262.4810126582278
                ],
                [
                    482.0253164556962,
                    260.86075949367086
                ],
                [
                    501.4683544303797,
                    267.34177215189874
                ],
                [
                    516.8607594936709,
                    289.2151898734177
                ],
                [
                    550.0759493670886,
                    298.9367088607595
                ],
                [
                    575.1898734177215,
                    298.126582278481
                ],
                [
                    595.4430379746835,
                    308.65822784810126
                ],
                [
                    618.126582278481,
                    345.11392405063293
                ],
                [
                    618.9367088607595,
                    359.69620253164555
                ],
                [
                    521.7215189873417,
                    433.4177215189873
                ],
                [
                    451.24050632911394,
                    422.88607594936707
                ],
                [
                    358.88607594936707,
                    372.65822784810126
                ],
                [
                    350.78481012658233,
                    337.0126582278481
                ],
                [
                    311.8987341772152,
                    345.11392405063293
                ],
                [
                    278.6835443037975,
                    345.9240506329114
                ],
                [
                    249.51898734177212,
                    339.44303797468353
                ],
                [
                    252.75949367088606,
                    357.2658227848101
                ],
                [
                    244.65822784810126,
                    377.5189873417722
                ],
                [
                    315.1392405063291,
                    371.8481012658228
                ],
                [
                    358.88607594936707,
                    372.65822784810126
                ],
                [
                    455.29113924050637,
                    430.17721518987344
                ],
                [
                    469.0632911392405,
                    465.0126582278481
                ],
                [
                    251.94936708860757,
                    574.379746835443
                ],
                [
                    132.0506329113924,
                    494.9873417721518
                ],
                [
                    145.8227848101266,
                    457.7215189873418
                ],
                [
                    157.1645569620253,
                    448.0
                ],
                [
                    80.20253164556962,
                    448.0
                ],
                [
                    31.594936708860757,
                    403.44303797468353
                ],
                [
                    37.265822784810126,
                    400.2025316455696
                ],
                [
                    53.46835443037975,
                    394.5316455696202
                ],
                [
                    46.177215189873415,
                    377.5189873417722
                ],
                [
                    0.810126582278481,
                    359.69620253164555
                ],
                [
                    1.620253164556962,
                    307.0379746835443
                ],
                [
                    33.21518987341772,
                    290.0253164556962
                ],
                [
                    88.30379746835445,
                    277.873417721519
                ],
                [
                    114.22784810126583,
                    272.2025316455696
                ],
                [
                    137.72151898734177,
                    271.3924050632911
                ],
                [
                    184.70886075949366,
                    284.3544303797468
                ],
                [
                    186.32911392405063,
                    276.253164556962
                ],
                [
                    202.53164556962025,
                    271.3924050632911
                ],
                [
                    204.96202531645568,
                    260.86075949367086
                ],
                [
                    194.4303797468354,
                    245.46835443037975
                ]
            ],
            "group_id": null,
            "shape_type": "polygon",
            "flags": {}
        }
    ],
    "imagePath": "ChickenPie28.jpg",
    "imageData": null,
    "imageHeight": 640,
    "imageWidth": 640
}