{
    "version": "5.0.1",
    "flags": {},
    "shapes": [
        {
            "label": "ChickenRice",
            "points": [
                [
                    588.2352905273438,
                    221.0491180419922
                ],
                [
                    623.5294189453125,
                    393.82049560546875
                ],
                [
                    564.7058715820312,
                    550.8853759765625
                ],
                [
                    472.941162109375,
                    613.7113647460938
                ],
                [
                    392.941162109375,
                    619.9939575195312
                ],
                [
                    310.5882263183594,
                    569.733154296875
                ],
                [
                    263.5294189453125,
                    616.8526611328125
                ],
                [
                    44.70588302612305,
                    497.48333740234375
                ],
                [
                    7.058823585510254,
                    453.5051574707031
                ],
                [
                    4.705882549285889,
                    321.5706481933594
                ],
                [
                    82.35294342041016,
                    161.3644561767578
                ],
                [
                    216.4705810546875,
                    57.701637268066406
                ],
                [
                    275.29412841796875,
                    51.41904067993164
                ],
                [
                    407.058837890625,
                    51.41904067993164
                ],
                [
                    534.11767578125,
                    136.2340850830078
                ]
            ],
            "group_id": null,
            "shape_type": "polygon",
            "flags": {}
        }
    ],
    "imagePath": "ChickenRice22_aug_0.jpg",
    "imageData": null,
    "imageHeight": 640,
    "imageWidth": 640
}