{
    "version": "5.0.1",
    "flags": {},
    "shapes": [
        {
            "label": "ChickenRice",
            "points": [
                [
                    557.6470336914062,
                    387.53790283203125
                ],
                [
                    562.3529663085938,
                    356.12493896484375
                ],
                [
                    581.1764526367188,
                    330.9945373535156
                ],
                [
                    600.0,
                    239.89691162109375
                ],
                [
                    489.4117736816406,
                    101.6798095703125
                ],
                [
                    390.5882263183594,
                    63.98423385620117
                ],
                [
                    256.4705810546875,
                    129.9514923095703
                ],
                [
                    225.88235473632812,
                    107.96240234375
                ],
                [
                    162.35293579101562,
                    158.22315979003906
                ],
                [
                    145.88235473632812,
                    230.47300720214844
                ],
                [
                    75.29412078857422,
                    287.0163879394531
                ],
                [
                    77.64705657958984,
                    368.69012451171875
                ],
                [
                    84.70587921142578,
                    453.5051574707031
                ],
                [
                    112.94117736816406,
                    459.7877502441406
                ],
                [
                    127.05882263183594,
                    532.03759765625
                ],
                [
                    183.5294189453125,
                    576.0157470703125
                ],
                [
                    218.8235321044922,
                    576.0157470703125
                ],
                [
                    282.3529357910156,
                    619.9939575195312
                ],
                [
                    343.5294189453125,
                    610.570068359375
                ],
                [
                    418.8235168457031,
                    572.8744506835938
                ],
                [
                    461.1764831542969,
                    588.5809326171875
                ],
                [
                    555.2941284179688,
                    522.6137084960938
                ],
                [
                    524.7058715820312,
                    459.7877502441406
                ],
                [
                    590.5882568359375,
                    415.8095703125
                ]
            ],
            "group_id": null,
            "shape_type": "polygon",
            "flags": {}
        }
    ],
    "imagePath": "ChickenRice10_aug_7.jpg",
    "imageData": null,
    "imageHeight": 640,
    "imageWidth": 640
}