{
    "version": "5.0.1",
    "flags": {},
    "shapes": [
        {
            "label": "Coin",
            "points": [
                [
                    201.6361083984375,
                    347.2744140625
                ],
                [
                    214.96218872070312,
                    327.5118408203125
                ],
                [
                    243.11732482910156,
                    313.4824523925781
                ],
                [
                    273.4302673339844,
                    314.83575439453125
                ],
                [
                    304.2684326171875,
                    330.40283203125
                ],
                [
                    327.2418518066406,
                    355.8048400878906
                ],
                [
                    337.2936096191406,
                    386.6072082519531
                ],
                [
                    334.14898681640625,
                    412.8453063964844
                ],
                [
                    294.5026550292969,
                    440.6251525878906
                ],
                [
                    254.77879333496094,
                    431.7200012207031
                ],
                [
                    226.57028198242188,
                    414.7796936035156
                ],
                [
                    205.1812286376953,
                    379.11614990234375
                ],
                [
                    201.34237670898438,
                    351.1340637207031
                ]
            ],
            "group_id": null,
            "shape_type": "polygon",
            "flags": {}
        }
    ],
    "imagePath": "Coin42_aug_6.jpg",
    "imageData": null,
    "imageHeight": 640,
    "imageWidth": 640
}