{
    "version": "5.0.1",
    "flags": {},
    "shapes": [
        {
            "label": "Coin",
            "points": [
                [
                    285.6289978027344,
                    330.45196533203125
                ],
                [
                    311.806396484375,
                    325.3521423339844
                ],
                [
                    333.7615966796875,
                    314.30255126953125
                ],
                [
                    341.36151123046875,
                    295.60321044921875
                ],
                [
                    337.1393127441406,
                    276.9039306640625
                ],
                [
                    321.0951232910156,
                    262.4544372558594
                ],
                [
                    303.362060546875,
                    255.65472412109375
                ],
                [
                    273.80694580078125,
                    253.9547576904297
                ],
                [
                    245.94070434570312,
                    266.7043151855469
                ],
                [
                    234.9630889892578,
                    285.40362548828125
                ],
                [
                    235.80752563476562,
                    307.5027770996094
                ],
                [
                    262.8293151855469,
                    326.2021179199219
                ]
            ],
            "group_id": null,
            "shape_type": "polygon",
            "flags": {}
        }
    ],
    "imagePath": "Coin33_aug_4.jpg",
    "imageData": null,
    "imageHeight": 640,
    "imageWidth": 640
}