{
    "version": "5.0.1",
    "flags": {},
    "shapes": [
        {
            "label": "FriedMeeSiam",
            "points": [
                [
                    138.7841796875,
                    527.0103149414062
                ],
                [
                    68.06309509277344,
                    528.0340576171875
                ],
                [
                    54.10531997680664,
                    451.7264404296875
                ],
                [
                    115.79216003417969,
                    359.55621337890625
                ],
                [
                    187.52493286132812,
                    282.16766357421875
                ],
                [
                    208.97850036621094,
                    223.8102264404297
                ],
                [
                    256.2154541015625,
                    181.6814727783203
                ],
                [
                    298.8449401855469,
                    130.52757263183594
                ],
                [
                    373.5567321777344,
                    81.00943756103516
                ],
                [
                    443.1938171386719,
                    102.34547424316406
                ],
                [
                    556.7724609375,
                    77.54644012451172
                ],
                [
                    639.0,
                    397.4185485839844
                ],
                [
                    611.0861206054688,
                    497.3241882324219
                ],
                [
                    553.2205200195312,
                    479.4598083496094
                ],
                [
                    499.5196533203125,
                    504.03009033203125
                ],
                [
                    495.5289611816406,
                    552.5244750976562
                ],
                [
                    365.3523864746094,
                    596.2260131835938
                ],
                [
                    239.81256103515625,
                    631.8718872070312
                ],
                [
                    129.68020629882812,
                    604.6619873046875
                ],
                [
                    159.67327880859375,
                    540.9970092773438
                ]
            ],
            "group_id": null,
            "shape_type": "polygon",
            "flags": {}
        }
    ],
    "imagePath": "FriedMeeSiam87_aug_1.jpg",
    "imageData": null,
    "imageHeight": 640,
    "imageWidth": 640
}