{
    "version": "5.0.1",
    "flags": {},
    "shapes": [
        {
            "label": "GrilledSalmon",
            "points": [
                [
                    224.13345336914062,
                    528.9829711914062
                ],
                [
                    454.76666259765625,
                    522.4725952148438
                ],
                [
                    584.1890869140625,
                    481.3352966308594
                ],
                [
                    566.2890014648438,
                    425.8351135253906
                ],
                [
                    493.1939697265625,
                    365.8125915527344
                ],
                [
                    370.296142578125,
                    322.7897644042969
                ],
                [
                    248.43617248535156,
                    342.3074035644531
                ],
                [
                    142.66702270507812,
                    404.17083740234375
                ],
                [
                    148.45706176757812,
                    446.2649841308594
                ]
            ],
            "group_id": null,
            "shape_type": "polygon",
            "flags": {}
        },
        {
            "label": "GrilledSalmon",
            "points": [
                [
                    0.0,
                    367.9366455078125
                ],
                [
                    122.64383697509766,
                    337.1645812988281
                ],
                [
                    243.20114135742188,
                    319.96112060546875
                ],
                [
                    316.36767578125,
                    298.01202392578125
                ],
                [
                    320.2875671386719,
                    277.40740966796875
                ],
                [
                    285.1029357910156,
                    235.69924926757812
                ],
                [
                    229.25662231445312,
                    202.87051391601562
                ],
                [
                    179.4173583984375,
                    201.92906188964844
                ],
                [
                    125.85078430175781,
                    179.78219604492188
                ],
                [
                    93.11524963378906,
                    193.19680786132812
                ],
                [
                    59.667884826660156,
                    187.68768310546875
                ],
                [
                    5.896788597106934,
                    221.01275634765625
                ],
                [
                    0.0,
                    366.0691833496094
                ]
            ],
            "group_id": null,
            "shape_type": "polygon",
            "flags": {}
        },
        {
            "label": "GrilledSalmon",
            "points": [
                [
                    549.4380493164062,
                    360.2863464355469
                ],
                [
                    639.0,
                    348.31646728515625
                ],
                [
                    639.0,
                    229.95062255859375
                ],
                [
                    586.5025024414062,
                    215.3232421875
                ],
                [
                    495.3277587890625,
                    245.80262756347656
                ],
                [
                    431.36444091796875,
                    273.77264404296875
                ],
                [
                    463.66650390625,
                    339.6988220214844
                ],
                [
                    503.808349609375,
                    364.4158020019531
                ]
            ],
            "group_id": null,
            "shape_type": "polygon",
            "flags": {}
        }
    ],
    "imagePath": "GrilledSalmon67_aug_3.jpg",
    "imageData": null,
    "imageHeight": 640,
    "imageWidth": 640
}