{
    "version": "5.0.1",
    "flags": {},
    "shapes": [
        {
            "label": "HokkienMee",
            "points": [
                [
                    181.64706420898438,
                    362.21807861328125
                ],
                [
                    161.5386199951172,
                    308.4443664550781
                ],
                [
                    162.68118286132812,
                    254.1356964111328
                ],
                [
                    193.75308227539062,
                    210.1630401611328
                ],
                [
                    224.31422424316406,
                    175.2693328857422
                ],
                [
                    243.71380615234375,
                    160.69544982910156
                ],
                [
                    279.8997802734375,
                    153.71450805664062
                ],
                [
                    365.5246887207031,
                    143.77696228027344
                ],
                [
                    435.8536682128906,
                    166.13092041015625
                ],
                [
                    479.9011535644531,
                    205.58612060546875
                ],
                [
                    507.972412109375,
                    261.9025573730469
                ],
                [
                    501.5638732910156,
                    345.0596008300781
                ],
                [
                    471.6059265136719,
                    469.6069641113281
                ],
                [
                    421.0354309082031,
                    489.44024658203125
                ],
                [
                    363.62921142578125,
                    467.2667541503906
                ],
                [
                    276.87933349609375,
                    434.0616455078125
                ],
                [
                    214.03326416015625,
                    393.6399841308594
                ]
            ],
            "group_id": null,
            "shape_type": "polygon",
            "flags": {}
        }
    ],
    "imagePath": "HokkienMee40_aug_5.jpg",
    "imageData": null,
    "imageHeight": 640,
    "imageWidth": 640
}