{
    "version": "5.0.1",
    "flags": {},
    "shapes": [
        {
            "label": "HokkienMee",
            "points": [
                [
                    15.39240506329114,
                    203.34177215189874
                ],
                [
                    114.22784810126583,
                    84.25316455696202
                ],
                [
                    234.126582278481,
                    32.40506329113924
                ],
                [
                    453.6708860759494,
                    47.79746835443038
                ],
                [
                    592.2025316455696,
                    190.37974683544303
                ],
                [
                    640.0,
                    272.2025316455696
                ],
                [
                    639.1898734177215,
                    640.0
                ],
                [
                    69.67088607594937,
                    631.0886075949367
                ],
                [
                    0.0,
                    550.8860759493671
                ],
                [
                    0.0,
                    223.59493670886076
                ]
            ],
            "group_id": null,
            "shape_type": "polygon",
            "flags": {}
        }
    ],
    "imagePath": "HokkienMee38.jpg",
    "imageData": null,
    "imageHeight": 640,
    "imageWidth": 640
}