{
    "version": "5.0.1",
    "flags": {},
    "shapes": [
        {
            "label": "Orange",
            "points": [
                [
                    154.21112060546875,
                    227.94662475585938
                ],
                [
                    163.35317993164062,
                    191.7320556640625
                ],
                [
                    176.3043975830078,
                    163.2227020263672
                ],
                [
                    199.9213409423828,
                    140.87754821777344
                ],
                [
                    222.77647399902344,
                    129.31971740722656
                ],
                [
                    251.72628784179688,
                    133.17233276367188
                ],
                [
                    271.5340576171875,
                    142.41860961914062
                ],
                [
                    286.7707824707031,
                    163.9932403564453
                ],
                [
                    302.0075378417969,
                    180.9447479248047
                ],
                [
                    306.57855224609375,
                    196.3551788330078
                ],
                [
                    302.0075378417969,
                    261.849609375
                ],
                [
                    302.7693786621094,
                    280.3421630859375
                ],
                [
                    280.67608642578125,
                    308.8514709472656
                ],
                [
                    263.9156799316406,
                    325.802978515625
                ],
                [
                    290.5799865722656,
                    343.5250244140625
                ],
                [
                    298.9602355957031,
                    363.5586242675781
                ],
                [
                    305.8167419433594,
                    383.59222412109375
                ],
                [
                    314.1969299316406,
                    443.6929931640625
                ],
                [
                    298.1983642578125,
                    496.8590087890625
                ],
                [
                    270.0103759765625,
                    534.6146240234375
                ],
                [
                    243.3460693359375,
                    551.566162109375
                ],
                [
                    215.91993713378906,
                    556.1892700195312
                ],
                [
                    188.49380493164062,
                    547.7135009765625
                ],
                [
                    159.54397583007812,
                    516.8926391601562
                ],
                [
                    136.68887329101562,
                    489.9243469238281
                ],
                [
                    129.8323211669922,
                    448.3161315917969
                ],
                [
                    135.16519165039062,
                    388.9858703613281
                ],
                [
                    148.11642456054688,
                    352.77130126953125
                ],
                [
                    168.68603515625,
                    327.3440856933594
                ],
                [
                    185.44644165039062,
                    318.8682861328125
                ],
                [
                    167.162353515625,
                    293.4410400390625
                ],
                [
                    158.02029418945312,
                    252.60333251953125
                ]
            ],
            "group_id": null,
            "shape_type": "polygon",
            "flags": {}
        }
    ],
    "imagePath": "Orange12_aug_2.jpg",
    "imageData": null,
    "imageHeight": 640,
    "imageWidth": 640
}