{
    "version": "5.0.1",
    "flags": {},
    "shapes": [
        {
            "label": "Orange",
            "points": [
                [
                    451.4837341308594,
                    191.00770568847656
                ],
                [
                    459.3106384277344,
                    231.36827087402344
                ],
                [
                    447.9260559082031,
                    283.7662048339844
                ],
                [
                    424.4454650878906,
                    324.8348693847656
                ],
                [
                    379.6188049316406,
                    348.2015075683594
                ],
                [
                    304.90771484375,
                    354.5742492675781
                ],
                [
                    245.13882446289062,
                    334.74798583984375
                ],
                [
                    206.71595764160156,
                    292.97125244140625
                ],
                [
                    196.75450134277344,
                    248.36219787597656
                ],
                [
                    210.2736358642578,
                    180.38650512695312
                ],
                [
                    242.2926788330078,
                    141.44207763671875
                ],
                [
                    277.8694152832031,
                    121.61582946777344
                ],
                [
                    319.8498840332031,
                    108.16231536865234
                ],
                [
                    385.3110656738281,
                    118.075439453125
                ],
                [
                    426.580078125,
                    149.23095703125
                ]
            ],
            "group_id": null,
            "shape_type": "polygon",
            "flags": {}
        }
    ],
    "imagePath": "Orange63_aug_5.jpg",
    "imageData": null,
    "imageHeight": 640,
    "imageWidth": 640
}