{
    "version": "5.0.1",
    "flags": {},
    "shapes": [
        {
            "label": "Orange",
            "points": [
                [
                    59.25646209716796,
                    144.67337036132812
                ],
                [
                    53.43294906616211,
                    134.18756103515625
                ],
                [
                    49.06531524658203,
                    117.98226165771484
                ],
                [
                    50.31321334838867,
                    97.96395111083984
                ],
                [
                    57.3846206665039,
                    81.18668365478516
                ],
                [
                    76.51901245117188,
                    65.55332946777344
                ],
                [
                    97.73323822021484,
                    60.2151107788086
                ],
                [
                    109.58824157714844,
                    56.592742919921875
                ],
                [
                    129.3466033935547,
                    60.2151107788086
                ],
                [
                    153.88853454589844,
                    73.56065368652344
                ],
                [
                    166.78346252441406,
                    85.95294952392578
                ],
                [
                    176.76661682128906,
                    107.49647521972656
                ],
                [
                    173.2309112548828,
                    133.61561584472656
                ],
                [
                    150.76878356933594,
                    155.73109436035156
                ],
                [
                    123.52308654785156,
                    166.21690368652344
                ],
                [
                    89.62191009521484,
                    165.6449432373047
                ],
                [
                    67.99172973632812,
                    154.968505859375
                ]
            ],
            "group_id": null,
            "shape_type": "polygon",
            "flags": {}
        }
    ],
    "imagePath": "Orange81_aug_2.jpg",
    "imageData": null,
    "imageHeight": 225,
    "imageWidth": 225
}