{
    "version": "5.0.1",
    "flags": {},
    "shapes": [
        {
            "label": "Tiramisu",
            "points": [
                [
                    217.49285888671875,
                    426.7342529296875
                ],
                [
                    183.67605590820312,
                    385.52001953125
                ],
                [
                    167.82443237304688,
                    211.15219116210938
                ],
                [
                    329.5109558105469,
                    0.0
                ],
                [
                    629.6349487304688,
                    118.15602111816406
                ],
                [
                    618.010498046875,
                    326.34063720703125
                ],
                [
                    549.3201293945312,
                    424.6207275390625
                ],
                [
                    570.4556274414062,
                    534.5252685546875
                ],
                [
                    537.6956176757812,
                    639.0
                ],
                [
                    343.2490539550781,
                    639.0
                ],
                [
                    307.3186950683594,
                    499.6517333984375
                ]
            ],
            "group_id": null,
            "shape_type": "polygon",
            "flags": {}
        }
    ],
    "imagePath": "Tiramisu95_aug_1.jpg",
    "imageData": null,
    "imageHeight": 640,
    "imageWidth": 640
}