{
    "version": "5.0.1",
    "flags": {},
    "shapes": [
        {
            "label": "Tiramisu",
            "points": [
                [
                    86.8510971069336,
                    300.09698486328125
                ],
                [
                    129.8806915283203,
                    217.41995239257812
                ],
                [
                    227.30621337890625,
                    198.7770538330078
                ],
                [
                    365.32568359375,
                    208.5037841796875
                ],
                [
                    444.8898620605469,
                    210.12490844726562
                ],
                [
                    486.2956848144531,
                    293.6125183105469
                ],
                [
                    483.86004638671875,
                    326.8454284667969
                ],
                [
                    535.0084838867188,
                    386.0162658691406
                ],
                [
                    524.4540405273438,
                    415.1964111328125
                ],
                [
                    509.0283203125,
                    413.57525634765625
                ],
                [
                    519.5828247070312,
                    441.9448547363281
                ],
                [
                    486.2956848144531,
                    468.69329833984375
                ],
                [
                    467.62249755859375,
                    508.41070556640625
                ],
                [
                    327.9792785644531,
                    533.5380249023438
                ],
                [
                    231.36561584472656,
                    512.4635009765625
                ],
                [
                    117.7025146484375,
                    488.957275390625
                ],
                [
                    100.65303802490234,
                    479.2305603027344
                ],
                [
                    95.7817611694336,
                    407.0907897949219
                ],
                [
                    57.623443603515625,
                    370.6156005859375
                ],
                [
                    68.98975372314453,
                    305.7709045410156
                ]
            ],
            "group_id": null,
            "shape_type": "polygon",
            "flags": {}
        }
    ],
    "imagePath": "Tiramisu61_aug_5.jpg",
    "imageData": null,
    "imageHeight": 640,
    "imageWidth": 640
}