{
    "version": "5.0.1",
    "flags": {},
    "shapes": [
        {
            "label": "FriedMeeSiam",
            "points": [
                [
                    94.7848129272461,
                    334.582275390625
                ],
                [
                    89.11392211914062,
                    230.07594299316406
                ],
                [
                    126.37974548339844,
                    129.62025451660156
                ],
                [
                    216.30380249023438,
                    141.77215576171875
                ],
                [
                    257.6202392578125,
                    68.0506362915039
                ],
                [
                    307.8481140136719,
                    58.3291130065918
                ],
                [
                    347.5443115234375,
                    85.87342071533203
                ],
                [
                    370.22784423828125,
                    66.43038177490234
                ],
                [
                    440.7088623046875,
                    78.582275390625
                ],
                [
                    463.39239501953125,
                    126.37974548339844
                ],
                [
                    450.4303894042969,
                    150.6835479736328
                ],
                [
                    507.1392517089844,
                    157.9746856689453
                ],
                [
                    517.6708984375,
                    217.92405700683594
                ],
                [
                    528.2025146484375,
                    298.93670654296875
                ],
                [
                    557.3670654296875,
                    513.6202392578125
                ],
                [
                    433.417724609375,
                    554.1265869140625
                ],
                [
                    269.77215576171875,
                    552.50634765625
                ],
                [
                    115.84809875488281,
                    533.8734130859375
                ],
                [
                    79.39240264892578,
                    418.02532958984375
                ]
            ],
            "group_id": null,
            "shape_type": "polygon",
            "flags": {}
        }
    ],
    "imagePath": "VQ4B22SLUPEWBF6OGIGB1V9P_aug_3.jpg",
    "imageData": null,
    "imageHeight": 640,
    "imageWidth": 640
}