{
    "version": "5.0.1",
    "flags": {},
    "shapes": [
        {
            "label": "Waffle",
            "points": [
                [
                    147.28314208984375,
                    361.2200622558594
                ],
                [
                    125.7063217163086,
                    318.19451904296875
                ],
                [
                    114.58496856689453,
                    293.6148986816406
                ],
                [
                    127.18531036376953,
                    244.09707641601562
                ],
                [
                    154.4412078857422,
                    196.51927185058594
                ],
                [
                    207.62770080566406,
                    161.1063995361328
                ],
                [
                    250.19866943359375,
                    152.09791564941406
                ],
                [
                    276.9936218261719,
                    147.5840606689453
                ],
                [
                    351.9490051269531,
                    162.8798828125
                ],
                [
                    410.654541015625,
                    184.2197723388672
                ],
                [
                    457.8866271972656,
                    218.14720153808594
                ],
                [
                    497.7749328613281,
                    276.0908203125
                ],
                [
                    523.8272094726562,
                    323.8735046386719
                ],
                [
                    485.6740417480469,
                    407.0882873535156
                ],
                [
                    454.76220703125,
                    441.6880187988281
                ],
                [
                    344.97662353515625,
                    468.2652893066406
                ],
                [
                    242.43240356445312,
                    446.2275085449219
                ],
                [
                    166.21566772460938,
                    390.7297058105469
                ]
            ],
            "group_id": null,
            "shape_type": "polygon",
            "flags": {}
        }
    ],
    "imagePath": "Waffle43_aug_5.jpg",
    "imageData": null,
    "imageHeight": 640,
    "imageWidth": 640
}