{
    "version": "5.0.1",
    "flags": {},
    "shapes": [
        {
            "label": "WhiteRice",
            "points": [
                [
                    0.0,
                    330.3057861328125
                ],
                [
                    18.842233657836914,
                    275.34161376953125
                ],
                [
                    16.55205726623535,
                    237.5537872314453
                ],
                [
                    84.11216735839844,
                    169.99365234375
                ],
                [
                    129.91561889648438,
                    113.8844223022461
                ],
                [
                    181.4445343017578,
                    111.59424591064453
                ],
                [
                    214.65203857421875,
                    66.93586730957031
                ],
                [
                    321.14508056640625,
                    32.58327102661133
                ],
                [
                    420.7676086425781,
                    54.33991241455078
                ],
                [
                    519.2450561523438,
                    110.44916534423828
                ],
                [
                    590.2404174804688,
                    178.00926208496094
                ],
                [
                    639.0,
                    230.68324279785156
                ],
                [
                    639.0,
                    290.2277526855469
                ],
                [
                    639.0,
                    329.16070556640625
                ],
                [
                    637.1890258789062,
                    518.0999755859375
                ],
                [
                    605.1265258789062,
                    554.7427368164062
                ],
                [
                    553.59765625,
                    613.1421508789062
                ],
                [
                    452.83001708984375,
                    639.0
                ],
                [
                    325.7254333496094,
                    639.0
                ],
                [
                    190.605224609375,
                    639.0
                ],
                [
                    74.95146942138672,
                    585.6600952148438
                ],
                [
                    9.681543350219727,
                    504.35894775390625
                ],
                [
                    0.0,
                    417.33233642578125
                ]
            ],
            "group_id": null,
            "shape_type": "polygon",
            "flags": {}
        }
    ],
    "imagePath": "Whiterice23_aug_4.jpg",
    "imageData": null,
    "imageHeight": 640,
    "imageWidth": 640
}