{
    "version": "5.0.1",
    "flags": {},
    "shapes": [
        {
            "label": "WhiteRice",
            "points": [
                [
                    163.8217010498047,
                    342.6630859375
                ],
                [
                    185.49945068359375,
                    293.3955078125
                ],
                [
                    187.96282958984375,
                    262.8495788574219
                ],
                [
                    210.6259307861328,
                    245.6059112548828
                ],
                [
                    216.53802490234375,
                    226.3915557861328
                ],
                [
                    237.2304229736328,
                    227.8695831298828
                ],
                [
                    257.4301452636719,
                    213.5819854736328
                ],
                [
                    300.29296875,
                    194.86029052734375
                ],
                [
                    331.82421875,
                    207.66986083984375
                ],
                [
                    364.3408508300781,
                    231.3183135986328
                ],
                [
                    388.4819641113281,
                    264.8202819824219
                ],
                [
                    403.75494384765625,
                    283.5419616699219
                ],
                [
                    406.2182922363281,
                    312.1171875
                ],
                [
                    414.10113525390625,
                    317.0439453125
                ],
                [
                    420.99859619140625,
                    352.0239562988281
                ],
                [
                    424.4472961425781,
                    382.5698547363281
                ],
                [
                    375.6723937988281,
                    444.64703369140625
                ],
                [
                    311.1318359375,
                    467.31011962890625
                ],
                [
                    258.4154968261719,
                    463.36871337890625
                ],
                [
                    210.13323974609375,
                    440.21295166015625
                ],
                [
                    173.6752166748047,
                    406.2182922363281
                ],
                [
                    161.3583221435547,
                    382.0771789550781
                ],
                [
                    160.3729705810547,
                    351.5312805175781
                ]
            ],
            "group_id": null,
            "shape_type": "polygon",
            "flags": {}
        }
    ],
    "imagePath": "Whiterice8_aug_2.jpg",
    "imageData": null,
    "imageHeight": 640,
    "imageWidth": 640
}