{
    "version": "5.0.1",
    "flags": {},
    "shapes": [
        {
            "label": "WhiteRice",
            "points": [
                [
                    169.7403564453125,
                    197.80735778808594
                ],
                [
                    209.0699462890625,
                    144.05169677734375
                ],
                [
                    299.0591735839844,
                    135.03173828125
                ],
                [
                    428.10528564453125,
                    159.39422607421875
                ],
                [
                    507.5928649902344,
                    208.4786376953125
                ],
                [
                    617.9503173828125,
                    306.0919494628906
                ],
                [
                    639.0,
                    366.3760681152344
                ],
                [
                    412.39111328125,
                    619.0925903320312
                ],
                [
                    295.7170104980469,
                    552.724365234375
                ],
                [
                    231.9630889892578,
                    487.1842041015625
                ],
                [
                    167.14157104492188,
                    394.5572204589844
                ],
                [
                    143.267822265625,
                    309.99017333984375
                ],
                [
                    149.65927124023438,
                    238.2735595703125
                ]
            ],
            "group_id": null,
            "shape_type": "polygon",
            "flags": {}
        }
    ],
    "imagePath": "Whiterice83_aug_1.jpg",
    "imageData": null,
    "imageHeight": 640,
    "imageWidth": 640
}